codelimit/__init__.py
codelimit/__main__.py
codelimit/github_auth.py
codelimit/utils.py
codelimit/version.py
codelimit/commands/__init__.py
codelimit/commands/app.py
codelimit/commands/check.py
codelimit/commands/findings.py
codelimit/commands/report.py
codelimit/commands/scan.py
codelimit/commands/upload.py
codelimit/common/CheckResult.py
codelimit/common/Codebase.py
codelimit/common/CodebseEntry.py
codelimit/common/Configuration.py
codelimit/common/GithubRepository.py
codelimit/common/Language.py
codelimit/common/LanguageTotals.py
codelimit/common/LanguageTotalsDelta.py
codelimit/common/Location.py
codelimit/common/Measurement.py
codelimit/common/ScanResultTable.py
codelimit/common/ScanTotals.py
codelimit/common/ScanTotalsDelta.py
codelimit/common/Scanner.py
codelimit/common/SourceFile.py
codelimit/common/SourceFileEntry.py
codelimit/common/SourceFolder.py
codelimit/common/SourceFolderEntry.py
codelimit/common/SummaryTable.py
codelimit/common/Token.py
codelimit/common/TokenRange.py
codelimit/common/__init__.py
codelimit/common/console.py
codelimit/common/lexer_utils.py
codelimit/common/source_utils.py
codelimit/common/token_utils.py
codelimit/common/utils.py
codelimit/common/gsm/Expression.py
codelimit/common/gsm/Pattern.py
codelimit/common/gsm/__init__.py
codelimit/common/gsm/matcher.py
codelimit/common/gsm/utils.py
codelimit/common/gsm/automata/Automata.py
codelimit/common/gsm/automata/DFA.py
codelimit/common/gsm/automata/NFA.py
codelimit/common/gsm/automata/State.py
codelimit/common/gsm/automata/__init__.py
codelimit/common/gsm/operator/Atom.py
codelimit/common/gsm/operator/Concat.py
codelimit/common/gsm/operator/OneOrMore.py
codelimit/common/gsm/operator/Operator.py
codelimit/common/gsm/operator/Optional.py
codelimit/common/gsm/operator/Union.py
codelimit/common/gsm/operator/ZeroOrMore.py
codelimit/common/gsm/operator/__init__.py
codelimit/common/gsm/predicate/Identity.py
codelimit/common/gsm/predicate/Predicate.py
codelimit/common/gsm/predicate/__init__.py
codelimit-1.0.1.dist-info/METADATA
codelimit-1.0.1.dist-info/WHEEL
codelimit-1.0.1.dist-info/entry_points.txt
codelimit-1.0.1.dist-info/licenses/LICENSE
codelimit-1.0.1.dist-info/RECORD
