Metadata-Version: 2.4
Name: codelimit
Version: 1.0.1
Author-email: Rob van der Leek <robvanderleek@gmail.com>
License-Expression: GPL-3.0-or-later
License-File: LICENSE
Requires-Python: <3.14,>=3.10
Requires-Dist: aiohttp<4,>=3.9.0
Requires-Dist: pathspec<0.13,>=0.12.1
Requires-Dist: pygments<3,>=2.13.0
Requires-Dist: pyperclip<2,>=1.9.0
Requires-Dist: pyyaml<7,>=6.0.1
Requires-Dist: requests<3,>=2.28.2
Requires-Dist: rich<14,>=13.7.1
Requires-Dist: sh<3,>=2.1.0
Requires-Dist: typer>=0.15.3
